hf/__init__.py
hf-1.3.2.dist-info/METADATA
hf-1.3.2.dist-info/WHEEL
hf-1.3.2.dist-info/entry_points.txt
hf-1.3.2.dist-info/top_level.txt
hf-1.3.2.dist-info/RECORD
