Metadata-Version: 2.4
Name: hf
Version: 1.3.2
Summary: CLI extracted from the huggingface_hub library to interact with the Hugging Face Hub
Home-page: https://github.com/huggingface/huggingface_hub
Author: Hugging Face, Inc.
Author-email: julien@huggingface.co
License: Apache
Requires-Python: >=3.9.0
Requires-Dist: huggingface_hub==1.3.2
Dynamic: author
Dynamic: author-email
Dynamic: description
Dynamic: description-content-type
Dynamic: home-page
Dynamic: license
Dynamic: requires-dist
Dynamic: requires-python
Dynamic: summary
